AIUT/__init__.py
AIUT/images/__init__.py
AIUT/images/about1.png
AIUT/images/cs.png
AIUT/images/doc.png
AIUT/images/folder_icon.png
AIUT/images/initial1.png
AIUT/images/java1.png
AIUT/images/logo.png
AIUT/images/py.png
AIUT/modules/AIUT_Core_CSharp.py
AIUT/modules/AIUT_Core_Java.py
AIUT/modules/AIUT_Core_Python.py
AIUT/modules/AIUT_Helper.py
AIUT/modules/__init__.py
AIUT/modules/sub.py
AIUT/requirements/__init__.py
AIUT/requirements/requirements.txt
AIUT/settings/UT_Settings.ini
AIUT/settings/__init__.py
AIUT/src/AIUT.py
AIUT/src/__init__.py
AIUT-1.4.dist-info/METADATA
AIUT-1.4.dist-info/WHEEL
AIUT-1.4.dist-info/entry_points.txt
AIUT-1.4.dist-info/license.txt
AIUT-1.4.dist-info/top_level.txt
AIUT-1.4.dist-info/RECORD
