Metadata-Version: 2.1
Name: AIUT
Version: 1.4
License-File: license.txt
Requires-Dist: Pillow
Requires-Dist: openai ==1.3.5
Requires-Dist: prettytable
